.gitignore
setup.py
munin/__init__.py
munin/client.py
pymunincli.egg-info/PKG-INFO
pymunincli.egg-info/SOURCES.txt
pymunincli.egg-info/dependency_links.txt
pymunincli.egg-info/top_level.txt