Metadata-Version: 1.1
Name: pymunincli
Version: 0.2
Summary: munin client library
Home-page: http://julien.danjou.info/software/pymunincli/
Author: Julien Danjou
Author-email: julien@danjou.info
License: GPL
Platform: UNKNOWN
Classifier: Development Status :: 2 - Pre-Alpha
Classifier: Intended Audience :: Developers
Classifier: Intended Audience :: Information Technology
Classifier: License :: OSI Approved :: GNU General Public License (GPL)
Classifier: Operating System :: OS Independent
Classifier: Programming Language :: Python
